setup.cfg
setup.py
apicheck/__init__.py
apicheck/apicheck.py
apicheck.egg-info/PKG-INFO
apicheck.egg-info/SOURCES.txt
apicheck.egg-info/dependency_links.txt
apicheck.egg-info/entry_points.txt
apicheck.egg-info/requires.txt
apicheck.egg-info/top_level.txt