Metadata-Version: 1.1
Name: apicheck
Version: 1.0.4
Summary: A Python tool and framework for testing JSON based web APIs
Home-page: https://github.com/kuykendb/APICheck
Author: Brad Kuykendall
Author-email: brad.kuykend@gmail.com
License: UNKNOWN
Download-URL: https://github.com/kuykendb/APICheck/tarball/v1.0-beta.1
Keywords: testing,api,web,json,test
Platform: UNKNOWN
